wordpress/__init__.py
wordpress/api.py
wordpress/auth.py
wordpress/helpers.py
wordpress/oauth.py
wordpress/transport.py
wordpress_api-1.2.8.dist-info/LICENSE.txt
wordpress_api-1.2.8.dist-info/METADATA
wordpress_api-1.2.8.dist-info/WHEEL
wordpress_api-1.2.8.dist-info/top_level.txt
wordpress_api-1.2.8.dist-info/RECORD
