Metadata-Version: 2.1
Name: wordpress-api
Version: 1.2.8
Summary: A Python wrapper for the Wordpress and WooCommerce REST APIs with oAuth1a 3leg support
Home-page: https://github.com/derwentx/wp-api-python
Author: Claudio Sanches @ Automattic, forked by Derwent @ Laserphile
Author-email: UNKNOWN
License: MIT License
Keywords: python wordpress woocommerce api development
Platform: any
Classifier: Development Status :: 5 - Production/Stable
Classifier: Intended Audience :: Developers
Classifier: Natural Language :: English
Classifier: License :: OSI Approved :: MIT License
Classifier: Programming Language :: Python
Classifier: Programming Language :: Python :: 2.7
Classifier: Programming Language :: Python :: 3.6
Classifier: Topic :: Software Development :: Libraries :: Python Modules
Requires-Dist: requests
Requires-Dist: requests-oauthlib
Requires-Dist: ordereddict
Requires-Dist: beautifulsoup4
Requires-Dist: lxml
Requires-Dist: six
